tubtools/__init__.py
tubtools/credentials.py
tubtools/extract.py
tubtools/login.py
tubtools/isis/__init__.py
tubtools/isis/assignments.py
tubtools/isis/common.py
tubtools/isis/grading.py
tubtools/isis/groups.py
tubtools/isis/participants.py
tubtools/isis/search.py
tubtools/moses/__init__.py
tubtools/moses/cli.py
tubtools/moses/people.py
tubtools-0.1.9.dist-info/LICENSE
tubtools-0.1.9.dist-info/METADATA
tubtools-0.1.9.dist-info/WHEEL
tubtools-0.1.9.dist-info/entry_points.txt
tubtools-0.1.9.dist-info/top_level.txt
tubtools-0.1.9.dist-info/RECORD
