Metadata-Version: 2.1
Name: tubtools
Version: 0.1.9
Summary: Scraping tools for the TU Berlin web portals
Home-page: https://git.tu-berlin.de/tkn/tubtools
Author: Sebastian Bräuer
Author-email: braeuer@tu-berlin.de
License: MIT
Classifier: Programming Language :: Python :: 3
Classifier: Development Status :: 3 - Alpha
Classifier: License :: OSI Approved :: MIT License
Requires-Python: >=3.7
License-File: LICENSE
Requires-Dist: fleep
Requires-Dist: requests
Requires-Dist: beautifulsoup4
Requires-Dist: keyring
